fn/__init__.py
fn/func.py
fn/iters.py
fn/monad.py
fn/op.py
fn/recur.py
fn/stream.py
fn/underscore.py
fn/uniform.py
fn/immutable/__init__.py
fn/immutable/finger.py
fn/immutable/heap.py
fn/immutable/list.py
fn/immutable/trie.py
fnmamoritai.py-0.5.2.dist-info/LICENSE
fnmamoritai.py-0.5.2.dist-info/METADATA
fnmamoritai.py-0.5.2.dist-info/WHEEL
fnmamoritai.py-0.5.2.dist-info/top_level.txt
fnmamoritai.py-0.5.2.dist-info/RECORD
