Metadata-Version: 2.1
Name: fnmamoritai.py
Version: 0.5.2
Summary: Implementation of missing features to enjoy functional programming in Python
Home-page: https://github.com/fnpy/fn.py
Author: fnpy team
Author-email: vash0the0stampede@gmail.com
License: Copyright 2013 Alexey Kachayev        
Keywords: functional,fp,utility
Platform: UNKNOWN
Classifier: Development Status :: 2 - Pre-Alpha
Classifier: Intended Audience :: Developers
Classifier: Natural Language :: English
Classifier: License :: OSI Approved :: Apache Software License
Classifier: Programming Language :: Python
Classifier: Programming Language :: Python :: 2.6
Classifier: Programming Language :: Python :: 2.7
Classifier: Programming Language :: Python :: 3
Classifier: Programming Language :: Python :: 3.3
Classifier: Programming Language :: Python :: 3.4
Classifier: Programming Language :: Python :: 3.5
License-File: LICENSE
